README.rst
setup.py
require/__init__.py
require/cmd.py
requirepy.egg-info/PKG-INFO
requirepy.egg-info/SOURCES.txt
requirepy.egg-info/dependency_links.txt
requirepy.egg-info/entry_points.txt
requirepy.egg-info/top_level.txt