Metadata-Version: 1.0
Name: requirepy
Version: 0.1.0
Summary: A better way to manage and import dependencies.
Home-page: https://github.com/kevinconway/require.py
Author: Kevin Conway
Author-email: kevinjacobconway@gmail.com
License: Apache2
Platform: UNKNOWN
